LICENSE
MANIFEST.in
README.rst
setup.py
hastl/__init__.py
hastl/build_stl.py
hastl/loess.py
hastl/stl.py
hastl.egg-info/PKG-INFO
hastl.egg-info/SOURCES.txt
hastl.egg-info/dependency_links.txt
hastl.egg-info/requires.txt
hastl.egg-info/top_level.txt
hastl/src/loess_c.c
hastl/src/loess_c.h
hastl/src/loess_c.json
hastl/src/loess_cuda.c
hastl/src/loess_cuda.h
hastl/src/loess_cuda.json
hastl/src/loess_multicore.c
hastl/src/loess_multicore.h
hastl/src/loess_multicore.json
hastl/src/loess_opencl.c
hastl/src/loess_opencl.h
hastl/src/loess_opencl.json
hastl/src/stl_c.c
hastl/src/stl_c.h
hastl/src/stl_c.json
hastl/src/stl_cuda.c
hastl/src/stl_cuda.h
hastl/src/stl_cuda.json
hastl/src/stl_multicore.c
hastl/src/stl_multicore.h
hastl/src/stl_multicore.json
hastl/src/stl_opencl.c
hastl/src/stl_opencl.h
hastl/src/stl_opencl.json